py_cdll/__init__.py
py_cdll/circular_doubly_linked_list.py
py_cdll/compare.py
py_cdll/exceptions.py
py_cdll/node.py
py_cdll-2025.10.9.12.57.dist-info/METADATA
py_cdll-2025.10.9.12.57.dist-info/WHEEL
py_cdll-2025.10.9.12.57.dist-info/RECORD
