Metadata-Version: 2.4
Name: py-cdll
Version: 2025.10.9.12.57
Summary: Circular doubly linked list data structure. Emulates Python list behavior and has additional features.
Author: tompy
Classifier: Development Status :: 3 - Alpha
Classifier: Intended Audience :: Developers
Classifier: License :: OSI Approved :: GNU General Public License v3 (GPLv3)
Classifier: Operating System :: OS Independent
Classifier: Programming Language :: Python :: 3.9
Requires-Python: >=3.9
